README.md
setup.py
ivp_enhanced/__init__.py
ivp_enhanced/ivp.py
ivp_enhanced/rk.py
ivp_enhanced.egg-info/PKG-INFO
ivp_enhanced.egg-info/SOURCES.txt
ivp_enhanced.egg-info/dependency_links.txt
ivp_enhanced.egg-info/top_level.txt